nglui/__init__.py
nglui/utils.py
nglui/parser/__init__.py
nglui/parser/base.py
nglui/parser/info.py
nglui/segmentprops/__init__.py
nglui/segmentprops/base.py
nglui/skeletons/__init__.py
nglui/skeletons/skeletons.py
nglui/statebuilder/__init__.py
nglui/statebuilder/base.py
nglui/statebuilder/helpers.py
nglui/statebuilder/ngl_annotations.py
nglui/statebuilder/ngl_components.py
nglui/statebuilder/shaders.py
nglui/statebuilder/site_utils.py
nglui/statebuilder/source_info.py
nglui/statebuilder/utils.py
nglui-4.6.1.dist-info/METADATA
nglui-4.6.1.dist-info/WHEEL
nglui-4.6.1.dist-info/licenses/LICENSE
nglui-4.6.1.dist-info/RECORD
