Metadata-Version: 2.4
Name: nglui
Version: 4.6.1
Summary: Framework for data-driven generation of neuroglancer states.
Project-URL: Homepage, https://caveconnectome.github.io/nglui/
Project-URL: Repository, https://github.com/CAVEconnectome/nglui.git
Project-URL: Changelog, https://caveconnectome.github.io/nglui/changelog/
Project-URL: Issues, https://github.com/CAVEconnectome/nglui/issues
Author: Forrest Collman
Author-email: Casey Schneider-Mizell <caseysm@gmail.com>
License-File: LICENSE
Classifier: Development Status :: 4 - Beta
Classifier: License :: OSI Approved :: MIT License
Classifier: Programming Language :: Python :: 3.8
Classifier: Programming Language :: Python :: 3.9
Classifier: Programming Language :: Python :: 3.10
Classifier: Programming Language :: Python :: 3.11
Classifier: Programming Language :: Python :: 3.12
Requires-Python: >=3.10
Requires-Dist: attrs>=24.6.1
Requires-Dist: cachetools>=5.5.2
Requires-Dist: caveclient>=7.0.0
Requires-Dist: ipython>=8.18.1
Requires-Dist: neuroglancer==2.40.1
Requires-Dist: numpy>=1.26.4
Requires-Dist: palettable<4.6.1,>=3.3.3
Requires-Dist: pandas>=2.2.3
Requires-Dist: pyperclip>=1.9.0
Requires-Dist: python-box>=7.2.0
Requires-Dist: requests>=2.32.3
Requires-Dist: six>=1.16.0
Requires-Dist: typing-extensions<5.0.0,>=4.13.2; python_full_version < '3.11'
Requires-Dist: webcolors>=24.11.1
Provides-Extra: full
Requires-Dist: cloud-volume>=12.3.1; extra == 'full'
